task_script_utils/__init__.py
task_script_utils/check_file_type.py
task_script_utils/convert_datetime_to_ts_format.py
task_script_utils/datetime_parser/README.md
task_script_utils/datetime_parser/__init__.py
task_script_utils/datetime_parser/datetime_config.py
task_script_utils/datetime_parser/datetime_info.py
task_script_utils/datetime_parser/flowcharts/parse.png
task_script_utils/datetime_parser/flowcharts/short-date-format-resolution.png
task_script_utils/datetime_parser/fractional_seconds_formatter.py
task_script_utils/datetime_parser/parse-white.png
task_script_utils/datetime_parser/parser.py
task_script_utils/datetime_parser/parser_exceptions.py
task_script_utils/datetime_parser/ts_datetime.py
task_script_utils/datetime_parser/tz_dicts.py
task_script_utils/datetime_parser/tz_list.py
task_script_utils/datetime_parser/utils/manipulation.py
task_script_utils/datetime_parser/utils/parsing.py
task_script_utils/extract_to_decorate.py
task_script_utils/is_number.py
task_script_utils/parquet.py
task_script_utils/parse.py
task_script_utils/plate_reader.py
task_script_utils/random.py
task_script_utils/uuid.py
task_script_utils/workflow_logging.py
ts_task_script_utils-2.3.3.dist-info/METADATA
ts_task_script_utils-2.3.3.dist-info/WHEEL
ts_task_script_utils-2.3.3.dist-info/licenses/LICENSE
ts_task_script_utils-2.3.3.dist-info/RECORD
