Metadata-Version: 2.4
Name: ts-task-script-utils
Version: 2.3.3
Summary: Python utility for Tetra Task Scripts
License: Apache-2.0
License-File: LICENSE
Author: Tetrascience
Author-email: developers@tetrascience.com
Requires-Python: >=3.9,<4
Classifier: License :: OSI Approved :: Apache Software License
Classifier: Operating System :: OS Independent
Classifier: Programming Language :: Python :: 3
Classifier: Programming Language :: Python :: 3.9
Classifier: Programming Language :: Python :: 3.10
Classifier: Programming Language :: Python :: 3.11
Classifier: Programming Language :: Python :: 3.12
Classifier: Programming Language :: Python :: 3.13
Classifier: Programming Language :: Python :: 3.14
Requires-Dist: arrow (>=1.2.2)
Requires-Dist: dateparser (>=1.1.1)
Requires-Dist: pendulum (>=3)
Requires-Dist: pydash (>=5.0.0)
Requires-Dist: python-dateutil (>=2.8.2)
Requires-Dist: typing-extensions (>=4.0.0)
